calliope_music-9.1.dist-info/METADATA
calliope_music-9.1.dist-info/WHEEL
calliope/__init__.py
calliope/__main__.py
calliope/cache.py
calliope/cli.py
calliope/config.py
calliope/database.py
calliope/interface.py
calliope/playlist.py
calliope/resolvers.py
calliope/sync_operation.py
calliope/utils.py
calliope/playlist-item.jsonschema
calliope/beets/__init__.py
calliope/diff/__init__.py
calliope/diff/compare.py
calliope/export/__init__.py
calliope/import_/__init__.py
calliope/shuffle/__init__.py
calliope/stat/__init__.py
calliope/sync/__init__.py
calliope/validate/__init__.py
calliope/bandcamp/__init__.py
calliope/lastfm/__init__.py
calliope/lastfm/history.py
calliope/lastfm/lastexport.py
calliope/listenbrainz/__init__.py
calliope/listenbrainz/api.py
calliope/listenbrainz/listens.py
calliope/musicbrainz/__init__.py
calliope/musicbrainz/annotate_helpers.py
calliope/musicbrainz/context.py
calliope/musicbrainz/includes.py
calliope/musicbrainz/resolve.py
calliope/musicbrainz/schema.py
calliope/play/__init__.py
calliope/select/__init__.py
calliope/select/constraints.py
calliope/select/localsearch.py
calliope/spotify/__init__.py
calliope/spotify/schema.py
calliope/suggest/__init__.py
calliope/tracker/__init__.py
calliope/youtube/__init__.py
calliope/subprojects/__init__.py
calliope/apps/viewer/__init__.py
calliope/apps/viewer/app.py
calliope/apps/viewer/mainwindow.py
calliope/apps/viewer/playlistbox.py
calliope/apps/viewer/playlistmodel.py
calliope_examples/collectors/online-to-local.sh
calliope_examples/listen_history/discovered-this-year.sh
calliope_examples/listen_history/never-listened.sh
calliope_examples/listen_history/not-listened-this-year.sh
calliope_examples/listen_history/what-to-buy.sh
calliope_examples/simple/random.sh
calliope_examples/special_mix/__init__.py
calliope_examples/special_mix/__main__.py
calliope_examples/special_mix/special_mix.py
calliope-9.1-py3.10.egg-info
calliope/subprojects/bandcamp_api/.gitignore
calliope/subprojects/bandcamp_api/LICENSE
calliope/subprojects/bandcamp_api/README.md
calliope_music-9.1.dist-info/RECORD
