Metadata-Version: 2.1
Name: calliope-music
Version: 9.1
Summary: Toolkit for working with playlists of music.
Home-page: https://gitlab.com/samthursfield/calliope
Project-URL: Homepage, https://gitlab.com/samthursfield/calliope
Project-URL: Bug_tracker, https://gitlab.com/samthursfield/calliope/issues
Project-URL: Changelog, https://calliope-music.readthedocs.io/en/latest/changelog.html
Requires-Dist: click
Requires-Dist: jsonschema
Requires-Dist: parsedatetime
Requires-Dist: pyyaml>3.11
Requires-Dist: splitstream
Requires-Dist: beautifulsoup4; extra == "bandcamp"
Requires-Dist: lxml; extra == "bandcamp"
Requires-Dist: requests; extra == "bandcamp"
Requires-Dist: musicbrainzngs>=0.7; extra == "musicbrainz"
Requires-Dist: simpleai; extra == "select"
Requires-Dist: cachecontrol; extra == "spotify"
Requires-Dist: lockfile; extra == "spotify"
Requires-Dist: spotipy; extra == "spotify"
Requires-Dist: google-api-python-client; extra == "youtube"
Provides-Extra: bandcamp
Provides-Extra: musicbrainz
Provides-Extra: select
Provides-Extra: spotify
Provides-Extra: youtube
